genai789/__init__.py
genai789/p1.py
genai789/p10.py
genai789/p2.py
genai789/p3.py
genai789/p4.py
genai789/p5.py
genai789/p6.py
genai789/p7.py
genai789/p8.py
genai789/p9.py
genai789-0.2.1.dist-info/METADATA
genai789-0.2.1.dist-info/WHEEL
genai789-0.2.1.dist-info/top_level.txt
genai789-0.2.1.dist-info/RECORD
