Metadata-Version: 2.4
Name: genai789
Version: 0.2.1
Summary: A collection of 10 code programs as strings
Author: Your Name
Author-email: your.email@example.com
Requires-Python: >=3.6
Dynamic: author
Dynamic: author-email
Dynamic: requires-python
Dynamic: summary
